grammarbot/__init__.py
grammarbot/__version__.py
grammarbot-0.2.0.dist-info/LICENSE
grammarbot-0.2.0.dist-info/METADATA
grammarbot-0.2.0.dist-info/WHEEL
grammarbot-0.2.0.dist-info/top_level.txt
grammarbot-0.2.0.dist-info/RECORD
